pyexpect/__init__.py
pyexpect/internals.py
pyexpect/jasmine_js_compatibility.py
tests/__init__.py
tests/test_jasmine_js_compatibility.py
tests/test_matchers.py
tests/test_meta_functionality.py
tests/test_performance.py
pyexpect-1.0.22.dist-info/LICENSE
pyexpect-1.0.22.dist-info/METADATA
pyexpect-1.0.22.dist-info/WHEEL
pyexpect-1.0.22.dist-info/top_level.txt
pyexpect-1.0.22.dist-info/RECORD
