Metadata-Version: 2.1
Name: pyexpect
Version: 1.0.22
Summary: Python expectaton library
Home-page: https://github.com/dwt/pyexpect
Author: Martin Häcker
Author-email: spamfaenger@gmx.de
License: ISC
Classifier: Development Status :: 5 - Production/Stable
Classifier: Environment :: Console
Classifier: Intended Audience :: Developers
Classifier: License :: OSI Approved :: ISC License (ISCL)
Classifier: Programming Language :: Python
Classifier: Programming Language :: Python :: 2
Classifier: Programming Language :: Python :: 3
Classifier: Topic :: Software Development :: Testing
Classifier: Topic :: Software Development :: Quality Assurance
License-File: LICENSE
